setup.py
django_generate_scaffold.egg-info/PKG-INFO
django_generate_scaffold.egg-info/SOURCES.txt
django_generate_scaffold.egg-info/dependency_links.txt
django_generate_scaffold.egg-info/requires.txt
django_generate_scaffold.egg-info/top_level.txt
generate_scaffold/__init__.py
generate_scaffold/tests.py
generate_scaffold/generators/__init__.py
generate_scaffold/generators/base.py
generate_scaffold/generators/models.py
generate_scaffold/generators/templates.py
generate_scaffold/generators/urls.py
generate_scaffold/generators/views.py
generate_scaffold/management/__init__.py
generate_scaffold/management/transactions.py
generate_scaffold/management/verbosity.py
generate_scaffold/management/commands/__init__.py
generate_scaffold/management/commands/generatescaffold.py
generate_scaffold/utils/__init__.py
generate_scaffold/utils/cacheclear.py
generate_scaffold/utils/directories.py
generate_scaffold/utils/modules.py
generate_scaffold/utils/strings.py