Metadata-Version: 1.0
Name: django-generate-scaffold
Version: 0.0.3a0
Summary: Generate a Django model, views, URLconf, and templates on the command line in seconds.
Home-page: http://github.com/modocache/django-generate-scaffold
Author: modocache
Author-email: modocache@gmail.com
License: UNKNOWN
Keywords: django generate scaffold
Platform: UNKNOWN
Classifier: Development Status :: 3 - Alpha
Classifier: Environment :: Console
Classifier: Framework :: Django
Classifier: Intended Audience :: Developers
Classifier: License :: OSI Approved :: MIT License
Classifier: Operating System :: OS Independent
Classifier: Programming Language :: Python
Classifier: Topic :: Software Development :: Code Generators
